file_api_bundle/__init__.py
file_api_bundle/bundle.py
file_api_bundle-1.0.dist-info/LICENSE
file_api_bundle-1.0.dist-info/METADATA
file_api_bundle-1.0.dist-info/WHEEL
file_api_bundle-1.0.dist-info/top_level.txt
file_api_bundle-1.0.dist-info/RECORD
